scheduled_futures/__init__.py
scheduled_futures-1.1.0.dist-info/LICENSE
scheduled_futures-1.1.0.dist-info/METADATA
scheduled_futures-1.1.0.dist-info/WHEEL
scheduled_futures-1.1.0.dist-info/top_level.txt
scheduled_futures-1.1.0.dist-info/RECORD
