Metadata-Version: 2.1
Name: scheduled_futures
Version: 1.1.0
Summary: concurrent.futures extension with a ScheduledThreadPoolExecutor to handle delayed and periodic futures with rescheduling
Home-page: https://github.com/ConnorSMaynes/scheduled_futures
Author: Connor Sherwood Maynes
Author-email: connormaynes@gmail.com
License: MIT
Keywords: concurrent.futures,apscheduler,asyncio,periodic
Classifier: Programming Language :: Python :: 3
Classifier: Operating System :: OS Independent
Requires-Python: <4,>=3.5
License-File: LICENSE
